LICENSE.txt
MANIFEST.in
README.md
pyproject.toml
setup.cfg
setup.py
src/pyigor/__init__.py
src/pyigor/__main__.py
src/pyigor/pyigor.py
src/pyigor.egg-info/PKG-INFO
src/pyigor.egg-info/SOURCES.txt
src/pyigor.egg-info/dependency_links.txt
src/pyigor.egg-info/requires.txt
src/pyigor.egg-info/top_level.txt