Metadata-Version: 2.1
Name: pyigor
Version: 0.2.0
Summary: Bridging between Python and Igor Pro
Home-page: https://github.com/chocolate-icecream/pyigor
Author: chocolate-icecream
Project-URL: Bug Tracker, https://github.com/chocolate-icecream/pyigor/issues
Keywords: Igor
Classifier: Programming Language :: Python :: 3
Classifier: Programming Language :: Python :: 3 :: Only
Classifier: License :: OSI Approved :: MIT License
Classifier: Operating System :: MacOS :: MacOS X
Classifier: Operating System :: Microsoft :: Windows
Classifier: Development Status :: 3 - Alpha
Classifier: Intended Audience :: Science/Research
Classifier: Intended Audience :: Education
Requires-Python: >=3.6
License-File: LICENSE.txt
Requires-Dist: flask>=2.1
Requires-Dist: h5py>=3.0
